{
  "_class": "group",
  "booleanOperation": 0,
  "do_objectID": "632016C6-6773-4455-9343-8C5FC8BA7D99",
  "exportOptions": {
    "_class": "exportOptions",
    "do_objectID": "21863E4E-5EB0-48CF-894B-C6A029CCEE70",
    "exportFormats": [
    ],
    "includedLayerIds": [
    ],
    "layerOptions": 0,
    "shouldTrim": false
  },
  "frame": {
    "_class": "rect",
    "constrainProportions": false,
    "do_objectID": "F3E6BA30-ECAE-4567-AD8A-5C99634DB6BA",
    "height": 1155,
    "width": 601,
    "x": 674,
    "y": 134
  },
  "hasClickThrough": false,
  "isFixedToViewport": false,
  "isFlippedHorizontal": false,
  "isFlippedVertical": false,
  "isLocked": false,
  "isVisible": true,
  "layerListExpandedType": 0,
  "layers": [
    {
      "class": "text",
      "id": "58E2F372-59D1-4965-8358-15C9057F5264"
    },
    {
      "class": "group",
      "id": "0012D665-04C2-4957-9BD6-C8E4DE14309C"
    },
    {
      "class": "group",
      "id": "E3120705-B3FE-4482-92B2-F66128A0CB36"
    },
    {
      "class": "group",
      "id": "3E4C6272-D2D2-4DD4-91D8-2996ED7FD2AE"
    },
    {
      "class": "shapeGroup",
      "id": "6FBF6F8F-9484-4C9E-95B9-29F96F8324AC"
    },
    {
      "class": "shapeGroup",
      "id": "523EEE3E-FC28-47EB-9F9A-37BA301BFC6D"
    },
    {
      "class": "group",
      "id": "1119F563-34FC-4136-887D-A2C574519861"
    }
  ],
  "name": "Body",
  "nameIsFixed": true,
  "resizingConstraint": 63,
  "resizingType": 0,
  "rotation": 0,
  "shouldBreakMaskChain": false,
  "style": {
    "_class": "style",
    "do_objectID": "2CEFE711-F0EB-410F-B5BB-A4984016D2D2",
    "endMarkerType": 0,
    "miterLimit": 10,
    "startMarkerType": 0,
    "windingRule": 1
  }
}